dotfiles/__init__.py
dotfiles/command_calling.py
dotfiles/dot_mechanism.py
dotfiles/dotfiles.py
dotfiles/git_funcitons.py
dotmanager/__init__.py
dotmanager/command_calling.py
dotmanager/dot_mechanism.py
dotmanager/dotfiles.py
dotmanager/dotmanager.py
dotmanager/git_funcitons.py
npp_dotmanager-0.2.3.dist-info/DESCRIPTION.rst
npp_dotmanager-0.2.3.dist-info/METADATA
npp_dotmanager-0.2.3.dist-info/RECORD
npp_dotmanager-0.2.3.dist-info/WHEEL
npp_dotmanager-0.2.3.dist-info/entry_points.txt
npp_dotmanager-0.2.3.dist-info/metadata.json
npp_dotmanager-0.2.3.dist-info/top_level.txt
