Metadata-Version: 2.0
Name: npp-dotmanager
Version: 0.2.3
Summary: N+1th dotmanager manager with public and private repository and git support
Home-page: https://github.com/sxnwlfkk/dotmanager
Author: Saxon Wolfkok
Author-email: saxonwolfkok@gmail.com
License: GPL
Keywords: configuration setuptools dotmanager linux unix
Platform: UNKNOWN
Classifier: Development Status :: 4 - Beta
Classifier: Intended Audience :: Developers
Classifier: Topic :: System :: Archiving :: Backup
Classifier: License :: OSI Approved :: GNU General Public License v3 (GPLv3)
Classifier: Programming Language :: Python :: 3
Requires-Dist: pyyaml
